VisualFlow/__init__.py
VisualFlow/augmentations.py
VisualFlow/inference.py
VisualFlow/utils.py
VisualFlow/visualflow.py
VisualFlow-0.2.4.dist-info/LICENSE
VisualFlow-0.2.4.dist-info/METADATA
VisualFlow-0.2.4.dist-info/WHEEL
VisualFlow-0.2.4.dist-info/top_level.txt
VisualFlow-0.2.4.dist-info/RECORD
