Metadata-Version: 2.1
Name: VisualFlow
Version: 0.2.4
Summary: A Python library for object detection format conversion
Home-page: https://github.com/Ojas-Sharma/VisualFlow
Author: Ojas Sharma
Author-email: ojassharma1607@gmail.com
Keywords: object-detection cvtoolkit pascal-voc yolo coco computer-vision detr image-classification detection format conversion
Classifier: License :: OSI Approved :: MIT License
Classifier: Programming Language :: Python :: 3
Classifier: Programming Language :: Python :: 3.6
Classifier: Programming Language :: Python :: 3.7
Classifier: Programming Language :: Python :: 3.8
Classifier: Programming Language :: Python :: 3.9
License-File: LICENSE
Requires-Dist: numpy
Requires-Dist: opencv-python
Requires-Dist: pascal-voc-writer
Requires-Dist: tqdm
Requires-Dist: Pillow
Requires-Dist: ultralytics
Requires-Dist: torch
